geofence_checks/__init__.py
geofence_checks/geofence_detector.py
geofence_checks-0.1.1.dist-info/METADATA
geofence_checks-0.1.1.dist-info/WHEEL
geofence_checks-0.1.1.dist-info/top_level.txt
geofence_checks-0.1.1.dist-info/RECORD
